pydmps/__init__.py
pydmps/cs.py
pydmps/dmp.py
pydmps/dmp_discrete.py
pydmps/dmp_rhythmic.py
pydmps-0.2.dist-info/DESCRIPTION.rst
pydmps-0.2.dist-info/METADATA
pydmps-0.2.dist-info/RECORD
pydmps-0.2.dist-info/WHEEL
pydmps-0.2.dist-info/metadata.json
pydmps-0.2.dist-info/top_level.txt
